{
    "comments": [],
    "company": {
        "businessNumber": "103931473",
        "name": "Northland Utilities (NWT) Limited",
        "duns": "",
        "tradeName": {
            "en": "",
            "fr": ""
        },
        "website": "www.northlandutilities.com",
        "mailingAddress": {
            "fullAddress": {
                "en": "General Delivery 1 66 Woodland Drive, Hay River, Northwest Territories, X0E 1G1, Canada",
                "fr": "Poste restante 1 66 Woodland Entrain, Hay River, Territoires du Nord-Ouest, X0E 1G1, Canada"
            },
            "address1": null,
            "city": "Hay River",
            "postalZip": "X0E 1G1",
            "province": {
                "en": "Northwest Territories",
                "fr": "Territoires du Nord-Ouest"
            },
            "country": ""
        },
        "parentCompanies": [
            {
                "name": "ATCO Electric",
                "businessNumber": "100113513",
                "duns": "",
                "percentageOwned": "86.0000",
                "address": ""
            },
            {
                "name": "ATCO Electric",
                "businessNumber": "100113513",
                "duns": "",
                "percentageOwned": "50.0000",
                "address": ""
            },
            {
                "name": "ATCO Electric",
                "businessNumber": "100113513",
                "duns": "",
                "percentageOwned": "50.0000",
                "address": ""
            }
        ]
    },
    "contacts": [
        {
            "firstName": "Mike",
            "lastName": "Dembowski",
            "email": "mike.dembowski@atco.com",
            "phoneNumber": "867-874-6879",
            "extension": "",
            "position": "generation lead",
            "language": {
                "code": "E",
                "en": "English",
                "fr": "Anglais"
            }
        }
    ],
    "disposalsTransfers": [
        {
            "substance": {
                "cas": "11104-93-1",
                "npriPart": [
                    "4"
                ],
                "id": 13506,
                "en": "Nitrogen oxides (expressed as nitrogen dioxide)",
                "fr": "Oxydes d'azote (exprimés en dioxyde d'azote)"
            },
            "unitType": {
                "en": "tonnes",
                "fr": "tonnes"
            },
            "landfill": null,
            "treatment": null,
            "undergroundInjection": null,
            "offsiteLandFill": null,
            "offsiteUndergroundInjection": null,
            "offsiteLandApplicationFarming": null,
            "storage": null,
            "physicalTreatment": null,
            "chemicalTreatment": null,
            "biologicalTreatment": null,
            "incineration": null,
            "sewageTreatment": null,
            "tailings": null,
            "wasteRock": null,
            "offsiteTailings": null,
            "offsiteWasteRock": null,
            "recoveryEnergy": null,
            "recoverySolvents": null,
            "recoveryOrganics": null,
            "recoveryMetals": null,
            "recoveryInOrganic": null,
            "recoveryAcidBase": null,
            "recoveryCatalyst": null,
            "recoveryPollutionAbatementResidues": null,
            "refiningReuseOil": null,
            "recyclingOther": null
        },
        {
            "substance": {
                "cas": "NA - M10",
                "npriPart": [
                    "4"
                ],
                "id": 14240,
                "en": "PM2.5 - Particulate Matter <= 2.5 Micrometers",
                "fr": "PM2,5 - Matière particulaire <= 2,5 micromètres"
            },
            "unitType": {
                "en": "tonnes",
                "fr": "tonnes"
            },
            "landfill": null,
            "treatment": null,
            "undergroundInjection": null,
            "offsiteLandFill": null,
            "offsiteUndergroundInjection": null,
            "offsiteLandApplicationFarming": null,
            "storage": null,
            "physicalTreatment": null,
            "chemicalTreatment": null,
            "biologicalTreatment": null,
            "incineration": null,
            "sewageTreatment": null,
            "tailings": null,
            "wasteRock": null,
            "offsiteTailings": null,
            "offsiteWasteRock": null,
            "recoveryEnergy": null,
            "recoverySolvents": null,
            "recoveryOrganics": null,
            "recoveryMetals": null,
            "recoveryInOrganic": null,
            "recoveryAcidBase": null,
            "recoveryCatalyst": null,
            "recoveryPollutionAbatementResidues": null,
            "refiningReuseOil": null,
            "recyclingOther": null
        },
        {
            "substance": {
                "cas": "NA - M09",
                "npriPart": [
                    "4"
                ],
                "id": 14239,
                "en": "PM10 - Particulate Matter <= 10 Micrometers",
                "fr": "PM10 - Matière particulaire <= 10 micromètres"
            },
            "unitType": {
                "en": "tonnes",
                "fr": "tonnes"
            },
            "landfill": null,
            "treatment": null,
            "undergroundInjection": null,
            "offsiteLandFill": null,
            "offsiteUndergroundInjection": null,
            "offsiteLandApplicationFarming": null,
            "storage": null,
            "physicalTreatment": null,
            "chemicalTreatment": null,
            "biologicalTreatment": null,
            "incineration": null,
            "sewageTreatment": null,
            "tailings": null,
            "wasteRock": null,
            "offsiteTailings": null,
            "offsiteWasteRock": null,
            "recoveryEnergy": null,
            "recoverySolvents": null,
            "recoveryOrganics": null,
            "recoveryMetals": null,
            "recoveryInOrganic": null,
            "recoveryAcidBase": null,
            "recoveryCatalyst": null,
            "recoveryPollutionAbatementResidues": null,
            "refiningReuseOil": null,
            "recyclingOther": null
        }
    ],
    "egus": [],
    "facility": {
        "npriId": 25193,
        "ghgrpId": null,
        "name": "Northland Utilities Hay River",
        "portable": false,
        "isCase3": false,
        "isCase4": false,
        "numberOfEmployees": 7,
        "industry": {
            "naics6Primary": {
                "id": 221122,
                "en": "Electric power distribution",
                "fr": "Distribution d'électricité"
            },
            "naics6Secondary": {
                "id": 221112,
                "en": "Fossil-fuel electric power generation",
                "fr": "Production d'électricité à partir de combustibles fossiles"
            },
            "naics6Tertiary": null,
            "naics4": {
                "id": 2211,
                "en": "Electric power generation, transmission and distribution",
                "fr": "Production, transport et distribution d'électricité"
            },
            "naics2": {
                "id": 22,
                "en": "Utilities",
                "fr": "Services publics"
            },
            "keyIndustrialSector": {
                "en": "Electricity",
                "fr": "Électricité\r\n"
            }
        },
        "website": "www.northlandutilities.com",
        "physicalAddress": {
            "fullAddress": {
                "en": "1 Spruce Road, Hay River, Northwest Territories, X0E 0R6, Canada",
                "fr": "1 Spruce Chemin, Hay River, Territoires du Nord-Ouest, X0E 0R6, Canada"
            },
            "address1": "1 Spruce Road",
            "city": "Hay River",
            "postalZip": "X0E 0R6",
            "province": {
                "en": "Northwest Territories",
                "fr": "Territoires du Nord-Ouest"
            },
            "country": ""
        },
        "geographicAddress": {
            "latitude": 60.860838,
            "longitude": -115.732212,
            "censusSubdivision": {
                "en": "Hay River",
                "fr": "Hay River"
            },
            "censusArea": {
                "en": " ",
                "fr": " "
            },
            "economicArea": {
                "en": "Northwest Territories / Territoires du Nord-Ouest",
                "fr": "Northwest Territories / Territoires du Nord-Ouest"
            },
            "censusDivision": {
                "en": "Region 5",
                "fr": "Region 5"
            },
            "ecoZone": {
                "en": "Taiga Plain",
                "fr": "Taïga des plaines"
            },
            "drainageArea": {
                "en": "Great Slave Lake Drainage Area",
                "fr": "Aire de drainage du Grand lac des Esclaves"
            },
            "datum": 1983,
            "landsurvey": "06-33-136-10-W5",
            "topograph": "B-039-G/085-B-13",
            "additionalInformation": "Lot 793,794 Plan 397 Hay River"
        },
        "operatingSchedule": {
            "mon": true,
            "tue": true,
            "wed": true,
            "thu": true,
            "fri": true,
            "sat": false,
            "sun": false,
            "operatingHours": 8.0,
            "startTime": "08:00",
            "shutdownPeriods": []
        },
        "activities": [
            {
                "group": 1,
                "en": "None of the above",
                "fr": "Aucune des réponses ci-dessus"
            },
            {
                "group": 2,
                "en": "None of the above",
                "fr": "Aucune des réponses ci-dessus"
            }
        ],
        "otherPrograms": [],
        "permits": [],
        "formattedAddress": {
            "en": "1 Spruce Road, Hay River, Northwest Territories, X0E 0R6, Canada",
            "fr": "1 Spruce Chemin, Hay River, Territoires du Nord-Ouest, X0E 0R6, Canada"
        }
    },
    "ghgrpId": null,
    "npriId": 25193,
    "otherYears": [
        {
            "reportYear": 2015,
            "npriId": 25193,
            "reportTypes": [
                {
                    "id": 1,
                    "en": "NPRI Inventory",
                    "fr": "Inventaire de l’INRP"
                }
            ],
            "substanceSummary": [
                {
                    "substance": {
                        "cas": "11104-93-1",
                        "npriPart": [
                            "4"
                        ],
                        "id": 13506,
                        "en": "Nitrogen oxides (expressed as nitrogen dioxide)",
                        "fr": "Oxydes d'azote (exprimés en dioxyde d'azote)"
                    },
                    "unitType": {
                        "en": "tonnes",
                        "fr": "tonnes"
                    },
                    "comments": [
                        {
                            "type": {
                                "id": 201,
                                "en": "On-site releases comment",
                                "fr": "Commentaire sur les rejets sur le site"
                            },
                            "comment": "reduced generation for 2015"
                        }
                    ],
                    "releaseAir": 21.384,
                    "releaseWater": null,
                    "releaseLand": null,
                    "releaseAllMedia": null,
                    "onsiteDisposal": null,
                    "offsiteDisposal": null,
                    "offsiteTreatment": null,
                    "offsiteRecycling": null,
                    "threshold": {
                        "en": "Yes",
                        "fr": "Oui"
                    }
                },
                {
                    "substance": {
                        "cas": "NA - M10",
                        "npriPart": [
                            "4"
                        ],
                        "id": 14240,
                        "en": "PM2.5 - Particulate Matter <= 2.5 Micrometers",
                        "fr": "PM2,5 - Matière particulaire <= 2,5 micromètres"
                    },
                    "unitType": {
                        "en": "tonnes",
                        "fr": "tonnes"
                    },
                    "comments": [
                        {
                            "type": {
                                "id": 201,
                                "en": "On-site releases comment",
                                "fr": "Commentaire sur les rejets sur le site"
                            },
                            "comment": "reduced generation for 2015"
                        }
                    ],
                    "releaseAir": 0.32,
                    "releaseWater": null,
                    "releaseLand": null,
                    "releaseAllMedia": null,
                    "onsiteDisposal": null,
                    "offsiteDisposal": null,
                    "offsiteTreatment": null,
                    "offsiteRecycling": null,
                    "threshold": {
                        "en": "Yes",
                        "fr": "Oui"
                    }
                }
            ]
        },
        {
            "reportYear": 2014,
            "npriId": 25193,
            "reportTypes": [
                {
                    "id": 1,
                    "en": "NPRI Inventory",
                    "fr": "Inventaire de l’INRP"
                }
            ],
            "substanceSummary": [
                {
                    "substance": {
                        "cas": "11104-93-1",
                        "npriPart": [
                            "4"
                        ],
                        "id": 13506,
                        "en": "Nitrogen oxides (expressed as nitrogen dioxide)",
                        "fr": "Oxydes d'azote (exprimés en dioxyde d'azote)"
                    },
                    "unitType": {
                        "en": "tonnes",
                        "fr": "tonnes"
                    },
                    "comments": [
                        {
                            "type": {
                                "id": 201,
                                "en": "On-site releases comment",
                                "fr": "Commentaire sur les rejets sur le site"
                            },
                            "comment": "increased generation for 2014"
                        }
                    ],
                    "releaseAir": 27.046,
                    "releaseWater": null,
                    "releaseLand": null,
                    "releaseAllMedia": null,
                    "onsiteDisposal": null,
                    "offsiteDisposal": null,
                    "offsiteTreatment": null,
                    "offsiteRecycling": null,
                    "threshold": {
                        "en": "Yes",
                        "fr": "Oui"
                    }
                },
                {
                    "substance": {
                        "cas": "NA - M10",
                        "npriPart": [
                            "4"
                        ],
                        "id": 14240,
                        "en": "PM2.5 - Particulate Matter <= 2.5 Micrometers",
                        "fr": "PM2,5 - Matière particulaire <= 2,5 micromètres"
                    },
                    "unitType": {
                        "en": "tonnes",
                        "fr": "tonnes"
                    },
                    "comments": [
                        {
                            "type": {
                                "id": 201,
                                "en": "On-site releases comment",
                                "fr": "Commentaire sur les rejets sur le site"
                            },
                            "comment": "increased generation for 2014"
                        }
                    ],
                    "releaseAir": 0.405,
                    "releaseWater": null,
                    "releaseLand": null,
                    "releaseAllMedia": null,
                    "onsiteDisposal": null,
                    "offsiteDisposal": null,
                    "offsiteTreatment": null,
                    "offsiteRecycling": null,
                    "threshold": {
                        "en": "Yes",
                        "fr": "Oui"
                    }
                }
            ]
        },
        {
            "reportYear": 2013,
            "npriId": 25193,
            "reportTypes": [
                {
                    "id": 3,
                    "en": "NPRI DNMC",
                    "fr": "NRPCD de l’INRP"
                }
            ],
            "substanceSummary": []
        },
        {
            "reportYear": 2012,
            "npriId": 25193,
            "reportTypes": [
                {
                    "id": 1,
                    "en": "NPRI Inventory",
                    "fr": "Inventaire de l’INRP"
                }
            ],
            "substanceSummary": [
                {
                    "substance": {
                        "cas": "11104-93-1",
                        "npriPart": [
                            "4"
                        ],
                        "id": 13506,
                        "en": "Nitrogen oxides (expressed as nitrogen dioxide)",
                        "fr": "Oxydes d'azote (exprimés en dioxyde d'azote)"
                    },
                    "unitType": {
                        "en": "tonnes",
                        "fr": "tonnes"
                    },
                    "comments": [],
                    "releaseAir": 20.099,
                    "releaseWater": null,
                    "releaseLand": null,
                    "releaseAllMedia": null,
                    "onsiteDisposal": null,
                    "offsiteDisposal": null,
                    "offsiteTreatment": null,
                    "offsiteRecycling": null,
                    "threshold": {
                        "en": "Yes",
                        "fr": "Oui"
                    }
                },
                {
                    "substance": {
                        "cas": "NA - M10",
                        "npriPart": [
                            "4"
                        ],
                        "id": 14240,
                        "en": "PM2.5 - Particulate Matter <= 2.5 Micrometers",
                        "fr": "PM2,5 - Matière particulaire <= 2,5 micromètres"
                    },
                    "unitType": {
                        "en": "tonnes",
                        "fr": "tonnes"
                    },
                    "comments": [],
                    "releaseAir": 0.301,
                    "releaseWater": null,
                    "releaseLand": null,
                    "releaseAllMedia": null,
                    "onsiteDisposal": null,
                    "offsiteDisposal": null,
                    "offsiteTreatment": null,
                    "offsiteRecycling": null,
                    "threshold": {
                        "en": "Yes",
                        "fr": "Oui"
                    }
                }
            ]
        },
        {
            "reportYear": 2011,
            "npriId": 25193,
            "reportTypes": [
                {
                    "id": 1,
                    "en": "NPRI Inventory",
                    "fr": "Inventaire de l’INRP"
                }
            ],
            "substanceSummary": [
                {
                    "substance": {
                        "cas": "11104-93-1",
                        "npriPart": [
                            "4"
                        ],
                        "id": 13506,
                        "en": "Nitrogen oxides (expressed as nitrogen dioxide)",
                        "fr": "Oxydes d'azote (exprimés en dioxyde d'azote)"
                    },
                    "unitType": {
                        "en": "tonnes",
                        "fr": "tonnes"
                    },
                    "comments": [],
                    "releaseAir": 20.143,
                    "releaseWater": null,
                    "releaseLand": null,
                    "releaseAllMedia": null,
                    "onsiteDisposal": null,
                    "offsiteDisposal": null,
                    "offsiteTreatment": null,
                    "offsiteRecycling": null,
                    "threshold": {
                        "en": "Yes",
                        "fr": "Oui"
                    }
                },
                {
                    "substance": {
                        "cas": "NA - M10",
                        "npriPart": [
                            "4"
                        ],
                        "id": 14240,
                        "en": "PM2.5 - Particulate Matter <= 2.5 Micrometers",
                        "fr": "PM2,5 - Matière particulaire <= 2,5 micromètres"
                    },
                    "unitType": {
                        "en": "tonnes",
                        "fr": "tonnes"
                    },
                    "comments": [],
                    "releaseAir": 0.302,
                    "releaseWater": null,
                    "releaseLand": null,
                    "releaseAllMedia": null,
                    "onsiteDisposal": null,
                    "offsiteDisposal": null,
                    "offsiteTreatment": null,
                    "offsiteRecycling": null,
                    "threshold": {
                        "en": "Yes",
                        "fr": "Oui"
                    }
                }
            ]
        },
        {
            "reportYear": 2019,
            "npriId": 25193,
            "reportTypes": [
                {
                    "id": 3,
                    "en": "NPRI DNMC",
                    "fr": "NRPCD de l’INRP"
                }
            ],
            "substanceSummary": []
        },
        {
            "reportYear": 2017,
            "npriId": 25193,
            "reportTypes": [
                {
                    "id": 3,
                    "en": "NPRI DNMC",
                    "fr": "NRPCD de l’INRP"
                }
            ],
            "substanceSummary": []
        },
        {
            "reportYear": 2018,
            "npriId": 25193,
            "reportTypes": [
                {
                    "id": 3,
                    "en": "NPRI DNMC",
                    "fr": "NRPCD de l’INRP"
                }
            ],
            "substanceSummary": []
        },
        {
            "reportYear": 2016,
            "npriId": 25193,
            "reportTypes": [
                {
                    "id": 3,
                    "en": "NPRI DNMC",
                    "fr": "NRPCD de l’INRP"
                }
            ],
            "substanceSummary": []
        },
        {
            "reportYear": 2020,
            "npriId": 25193,
            "reportTypes": [
                {
                    "id": 1,
                    "en": "NPRI Inventory",
                    "fr": "Inventaire de l’INRP"
                }
            ],
            "substanceSummary": [
                {
                    "substance": {
                        "cas": "11104-93-1",
                        "npriPart": [
                            "4"
                        ],
                        "id": 13506,
                        "en": "Nitrogen oxides (expressed as nitrogen dioxide)",
                        "fr": "Oxydes d'azote (exprimés en dioxyde d'azote)"
                    },
                    "unitType": {
                        "en": "tonnes",
                        "fr": "tonnes"
                    },
                    "comments": [
                        {
                            "type": {
                                "id": 201,
                                "en": "On-site releases comment",
                                "fr": "Commentaire sur les rejets sur le site"
                            },
                            "comment": "change in duration of back up generation required in 2020"
                        }
                    ],
                    "releaseAir": 25.525,
                    "releaseWater": null,
                    "releaseLand": null,
                    "releaseAllMedia": null,
                    "onsiteDisposal": null,
                    "offsiteDisposal": null,
                    "offsiteTreatment": null,
                    "offsiteRecycling": null,
                    "threshold": {
                        "en": "Yes",
                        "fr": "Oui"
                    }
                },
                {
                    "substance": {
                        "cas": "NA - M10",
                        "npriPart": [
                            "4"
                        ],
                        "id": 14240,
                        "en": "PM2.5 - Particulate Matter <= 2.5 Micrometers",
                        "fr": "PM2,5 - Matière particulaire <= 2,5 micromètres"
                    },
                    "unitType": {
                        "en": "tonnes",
                        "fr": "tonnes"
                    },
                    "comments": [
                        {
                            "type": {
                                "id": 201,
                                "en": "On-site releases comment",
                                "fr": "Commentaire sur les rejets sur le site"
                            },
                            "comment": "change in duration of back up generation required in 2020"
                        }
                    ],
                    "releaseAir": 0.382,
                    "releaseWater": null,
                    "releaseLand": null,
                    "releaseAllMedia": null,
                    "onsiteDisposal": null,
                    "offsiteDisposal": null,
                    "offsiteTreatment": null,
                    "offsiteRecycling": null,
                    "threshold": {
                        "en": "Yes",
                        "fr": "Oui"
                    }
                }
            ]
        },
        {
            "reportYear": 2021,
            "npriId": 25193,
            "reportTypes": [
                {
                    "id": 3,
                    "en": "NPRI DNMC",
                    "fr": "NRPCD de l’INRP"
                }
            ],
            "substanceSummary": []
        },
        {
            "reportYear": 2023,
            "npriId": 25193,
            "reportTypes": [
                {
                    "id": 1,
                    "en": "NPRI Inventory",
                    "fr": "Inventaire de l’INRP"
                }
            ],
            "substanceSummary": [
                {
                    "substance": {
                        "cas": "11104-93-1",
                        "npriPart": [
                            "4"
                        ],
                        "id": 13506,
                        "en": "Nitrogen oxides (expressed as nitrogen dioxide)",
                        "fr": "Oxydes d'azote (exprimés en dioxyde d'azote)"
                    },
                    "unitType": {
                        "en": "tonnes",
                        "fr": "tonnes"
                    },
                    "comments": [],
                    "releaseAir": 255.589,
                    "releaseWater": null,
                    "releaseLand": null,
                    "releaseAllMedia": null,
                    "onsiteDisposal": null,
                    "offsiteDisposal": null,
                    "offsiteTreatment": null,
                    "offsiteRecycling": null,
                    "threshold": {
                        "en": "Yes",
                        "fr": "Oui"
                    }
                },
                {
                    "substance": {
                        "cas": "630-08-0",
                        "npriPart": [
                            "4"
                        ],
                        "id": 13873,
                        "en": "Carbon monoxide",
                        "fr": "Monoxyde de carbone"
                    },
                    "unitType": {
                        "en": "tonnes",
                        "fr": "tonnes"
                    },
                    "comments": [],
                    "releaseAir": 67.891,
                    "releaseWater": null,
                    "releaseLand": null,
                    "releaseAllMedia": null,
                    "onsiteDisposal": null,
                    "offsiteDisposal": null,
                    "offsiteTreatment": null,
                    "offsiteRecycling": null,
                    "threshold": {
                        "en": "Yes",
                        "fr": "Oui"
                    }
                },
                {
                    "substance": {
                        "cas": "NA - M09",
                        "npriPart": [
                            "4"
                        ],
                        "id": 14239,
                        "en": "PM10 - Particulate Matter <= 10 Micrometers",
                        "fr": "PM10 - Matière particulaire <= 10 micromètres"
                    },
                    "unitType": {
                        "en": "tonnes",
                        "fr": "tonnes"
                    },
                    "comments": [],
                    "releaseAir": 3.962,
                    "releaseWater": null,
                    "releaseLand": null,
                    "releaseAllMedia": null,
                    "onsiteDisposal": null,
                    "offsiteDisposal": null,
                    "offsiteTreatment": null,
                    "offsiteRecycling": null,
                    "threshold": {
                        "en": "Yes",
                        "fr": "Oui"
                    }
                },
                {
                    "substance": {
                        "cas": "NA - M10",
                        "npriPart": [
                            "4"
                        ],
                        "id": 14240,
                        "en": "PM2.5 - Particulate Matter <= 2.5 Micrometers",
                        "fr": "PM2,5 - Matière particulaire <= 2,5 micromètres"
                    },
                    "unitType": {
                        "en": "tonnes",
                        "fr": "tonnes"
                    },
                    "comments": [],
                    "releaseAir": 3.826,
                    "releaseWater": null,
                    "releaseLand": null,
                    "releaseAllMedia": null,
                    "onsiteDisposal": null,
                    "offsiteDisposal": null,
                    "offsiteTreatment": null,
                    "offsiteRecycling": null,
                    "threshold": {
                        "en": "Yes",
                        "fr": "Oui"
                    }
                }
            ]
        },
        {
            "reportYear": 2024,
            "npriId": 25193,
            "reportTypes": [
                {
                    "id": 1,
                    "en": "NPRI Inventory",
                    "fr": "Inventaire de l’INRP"
                }
            ],
            "substanceSummary": [
                {
                    "substance": {
                        "cas": "11104-93-1",
                        "npriPart": [
                            "4"
                        ],
                        "id": 13506,
                        "en": "Nitrogen oxides (expressed as nitrogen dioxide)",
                        "fr": "Oxydes d'azote (exprimés en dioxyde d'azote)"
                    },
                    "unitType": {
                        "en": "tonnes",
                        "fr": "tonnes"
                    },
                    "comments": [],
                    "releaseAir": 459.484,
                    "releaseWater": null,
                    "releaseLand": null,
                    "releaseAllMedia": null,
                    "onsiteDisposal": null,
                    "offsiteDisposal": null,
                    "offsiteTreatment": null,
                    "offsiteRecycling": null,
                    "threshold": {
                        "en": "Yes",
                        "fr": "Oui"
                    }
                },
                {
                    "substance": {
                        "cas": "630-08-0",
                        "npriPart": [
                            "4"
                        ],
                        "id": 13873,
                        "en": "Carbon monoxide",
                        "fr": "Monoxyde de carbone"
                    },
                    "unitType": {
                        "en": "tonnes",
                        "fr": "tonnes"
                    },
                    "comments": [],
                    "releaseAir": 122.051,
                    "releaseWater": null,
                    "releaseLand": null,
                    "releaseAllMedia": null,
                    "onsiteDisposal": null,
                    "offsiteDisposal": null,
                    "offsiteTreatment": null,
                    "offsiteRecycling": null,
                    "threshold": {
                        "en": "Yes",
                        "fr": "Oui"
                    }
                },
                {
                    "substance": {
                        "cas": "NA - M09",
                        "npriPart": [
                            "4"
                        ],
                        "id": 14239,
                        "en": "PM10 - Particulate Matter <= 10 Micrometers",
                        "fr": "PM10 - Matière particulaire <= 10 micromètres"
                    },
                    "unitType": {
                        "en": "tonnes",
                        "fr": "tonnes"
                    },
                    "comments": [],
                    "releaseAir": 7.122,
                    "releaseWater": null,
                    "releaseLand": null,
                    "releaseAllMedia": null,
                    "onsiteDisposal": null,
                    "offsiteDisposal": null,
                    "offsiteTreatment": null,
                    "offsiteRecycling": null,
                    "threshold": {
                        "en": "Yes",
                        "fr": "Oui"
                    }
                },
                {
                    "substance": {
                        "cas": "NA - M10",
                        "npriPart": [
                            "4"
                        ],
                        "id": 14240,
                        "en": "PM2.5 - Particulate Matter <= 2.5 Micrometers",
                        "fr": "PM2,5 - Matière particulaire <= 2,5 micromètres"
                    },
                    "unitType": {
                        "en": "tonnes",
                        "fr": "tonnes"
                    },
                    "comments": [],
                    "releaseAir": 6.88,
                    "releaseWater": null,
                    "releaseLand": null,
                    "releaseAllMedia": null,
                    "onsiteDisposal": null,
                    "offsiteDisposal": null,
                    "offsiteTreatment": null,
                    "offsiteRecycling": null,
                    "threshold": {
                        "en": "Yes",
                        "fr": "Oui"
                    }
                },
                {
                    "substance": {
                        "cas": "NA - M16",
                        "npriPart": [
                            "4"
                        ],
                        "id": 14242,
                        "en": "Volatile Organic Compounds (Total)",
                        "fr": "Composés organiques volatils (total)"
                    },
                    "unitType": {
                        "en": "tonnes",
                        "fr": "tonnes"
                    },
                    "comments": [],
                    "releaseAir": 11.76,
                    "releaseWater": null,
                    "releaseLand": null,
                    "releaseAllMedia": null,
                    "onsiteDisposal": null,
                    "offsiteDisposal": null,
                    "offsiteTreatment": null,
                    "offsiteRecycling": null,
                    "threshold": {
                        "en": "Yes",
                        "fr": "Oui"
                    }
                }
            ]
        }
    ],
    "p2Plan": {
        "hasP2Plan": true,
        "reasonsForPlan": [
            {
                "en": "Plan was prepared or implemented on a voluntary basis",
                "fr": "Plan préparé ou mis en œuvre volontairement"
            }
        ],
        "noticeType": [],
        "planComment": null,
        "recentlyUpdated": false,
        "planTargets": [],
        "hasActivities": true,
        "reasonsForNoActivities": [],
        "noActivitiesComment": null,
        "activityCategories": []
    },
    "releases": [
        {
            "substance": {
                "cas": "11104-93-1",
                "npriPart": [
                    "4"
                ],
                "id": 13506,
                "en": "Nitrogen oxides (expressed as nitrogen dioxide)",
                "fr": "Oxydes d'azote (exprimés en dioxyde d'azote)"
            },
            "unitType": {
                "en": "tonnes",
                "fr": "tonnes"
            },
            "stackPoint": 42.727,
            "storageHandling": null,
            "fugitive": null,
            "airSpills": null,
            "airOther": null,
            "roadDust": null,
            "directDischarges": null,
            "waterSpills": null,
            "waterLeaks": null,
            "landSpills": null,
            "landLeaks": null,
            "landOther": null,
            "allMedia": null
        },
        {
            "substance": {
                "cas": "NA - M10",
                "npriPart": [
                    "4"
                ],
                "id": 14240,
                "en": "PM2.5 - Particulate Matter <= 2.5 Micrometers",
                "fr": "PM2,5 - Matière particulaire <= 2,5 micromètres"
            },
            "unitType": {
                "en": "tonnes",
                "fr": "tonnes"
            },
            "stackPoint": 0.64,
            "storageHandling": null,
            "fugitive": null,
            "airSpills": null,
            "airOther": null,
            "roadDust": null,
            "directDischarges": null,
            "waterSpills": null,
            "waterLeaks": null,
            "landSpills": null,
            "landLeaks": null,
            "landOther": null,
            "allMedia": null
        },
        {
            "substance": {
                "cas": "NA - M09",
                "npriPart": [
                    "4"
                ],
                "id": 14239,
                "en": "PM10 - Particulate Matter <= 10 Micrometers",
                "fr": "PM10 - Matière particulaire <= 10 micromètres"
            },
            "unitType": {
                "en": "tonnes",
                "fr": "tonnes"
            },
            "stackPoint": 0.662,
            "storageHandling": null,
            "fugitive": null,
            "airSpills": null,
            "airOther": null,
            "roadDust": null,
            "directDischarges": null,
            "waterSpills": null,
            "waterLeaks": null,
            "landSpills": null,
            "landLeaks": null,
            "landOther": null,
            "allMedia": null
        }
    ],
    "reportTypes": [
        {
            "id": 1,
            "en": "NPRI Inventory",
            "fr": "Inventaire de l’INRP"
        }
    ],
    "reportYear": 2022,
    "scpDetails": [],
    "submissionDate": "2023-05-22T13:14:30.851472",
    "substanceSummary": [
        {
            "substance": {
                "cas": "11104-93-1",
                "npriPart": [
                    "4"
                ],
                "id": 13506,
                "en": "Nitrogen oxides (expressed as nitrogen dioxide)",
                "fr": "Oxydes d'azote (exprimés en dioxyde d'azote)"
            },
            "unitType": {
                "en": "tonnes",
                "fr": "tonnes"
            },
            "comments": [],
            "releaseAir": 42.727,
            "releaseWater": null,
            "releaseLand": null,
            "releaseAllMedia": null,
            "onsiteDisposal": null,
            "offsiteDisposal": null,
            "offsiteTreatment": null,
            "offsiteRecycling": null,
            "threshold": {
                "en": "Yes",
                "fr": "Oui"
            }
        },
        {
            "substance": {
                "cas": "NA - M09",
                "npriPart": [
                    "4"
                ],
                "id": 14239,
                "en": "PM10 - Particulate Matter <= 10 Micrometers",
                "fr": "PM10 - Matière particulaire <= 10 micromètres"
            },
            "unitType": {
                "en": "tonnes",
                "fr": "tonnes"
            },
            "comments": [
                {
                    "type": {
                        "id": 215,
                        "en": "Reason why substance was added to the report ",
                        "fr": "Raison pour laquelle la substance a été ajoutée au rapport "
                    },
                    "comment": "met threshold on particulate matter"
                }
            ],
            "releaseAir": 0.662,
            "releaseWater": null,
            "releaseLand": null,
            "releaseAllMedia": null,
            "onsiteDisposal": null,
            "offsiteDisposal": null,
            "offsiteTreatment": null,
            "offsiteRecycling": null,
            "threshold": {
                "en": "Yes",
                "fr": "Oui"
            }
        },
        {
            "substance": {
                "cas": "NA - M10",
                "npriPart": [
                    "4"
                ],
                "id": 14240,
                "en": "PM2.5 - Particulate Matter <= 2.5 Micrometers",
                "fr": "PM2,5 - Matière particulaire <= 2,5 micromètres"
            },
            "unitType": {
                "en": "tonnes",
                "fr": "tonnes"
            },
            "comments": [],
            "releaseAir": 0.64,
            "releaseWater": null,
            "releaseLand": null,
            "releaseAllMedia": null,
            "onsiteDisposal": null,
            "offsiteDisposal": null,
            "offsiteTreatment": null,
            "offsiteRecycling": null,
            "threshold": {
                "en": "Yes",
                "fr": "Oui"
            }
        }
    ]
}