{
    "year": 2022,
    "month": "08",
    "pt": "Saskatchewan",
    "includes_ghgrp": false,
    "volume_by_activity": {
        "DIFF": {
            "GAS": {
                "BT": 0.0,
                "CT": 0.0,
                "GP": 715.3,
                "GS": -322.8,
                "IF": 73.30000000000001,
                "PL": 1338.8,
                "TM": 0.0,
                "WT": 0.0
            },
            "SOLV": {
                "BT": 0.0,
                "IF": 5731.9
            },
            "WASTE": {
                "IF": 0.0
            },
            "WATER": {
                "BT": 0.0,
                "CT": 0.0,
                "GP": 0.0,
                "GS": 0.0,
                "IF": 63764.90000000002,
                "PL": -0.7,
                "TM": 0.0,
                "WT": -58841.5
            }
        },
        "DISP": {
            "C2-MX": {
                "GP": 129.1,
                "GS": 3.5,
                "PL": 101.1
            },
            "C2-SP": {
                "GP": 1211.9,
                "PL": 1211.9
            },
            "C3-MX": {
                "GP": 16317.1,
                "GS": 7.0,
                "PL": 9279.4
            },
            "C3-SP": {
                "GP": 9030.1,
                "TM": 9281.7
            },
            "C4-MX": {
                "GP": 835.5,
                "GS": 19.2
            },
            "C4-SP": {
                "GP": 8178.0,
                "TM": 22520.2
            },
            "C5-MX": {
                "GP": 1698.1,
                "GS": 66.0,
                "PL": 918.8
            },
            "C5-SP": {
                "GP": 0.0
            },
            "CO2": {
                "BT": 394.9
            },
            "CO2-MX": {
                "BT": 67151.0
            },
            "CO2-SP": {
                "PL": 35531.1
            },
            "COND": {
                "GP": 7503.2,
                "GS": 3076.1000000000004,
                "PL": 74642.1,
                "TM": 15152.4
            },
            "FSHWTR": {
                "IF": 23821.3,
                "WT": 3012335.4
            },
            "GAS": {
                "BT": 306952.20000000024,
                "GP": 63602.50000000001,
                "GS": 227088.60000000033,
                "PL": 4600417.399999999
            },
            "HELIUM": {
                "BT": 216.79999999999998,
                "GP": 179.2
            },
            "IC4-MX": {
                "GP": 1153.1000000000001,
                "PL": 656.7
            },
            "IC5-MX": {
                "GP": 55.3
            },
            "N2": {
                "BT": 27551.700000000008
            },
            "NC4-MX": {
                "GP": 1778.8,
                "PL": 1736.3
            },
            "OIL": {
                "BT": 1847070.5000000033,
                "CT": 166370.8,
                "GP": 1927.1000000000004,
                "IF": 1425.6000000000004,
                "PL": 3389522.6999999997,
                "TM": 1022974.4
            },
            "POLYMER": {
                "BT": 62116.6,
                "IF": 25224.6
            },
            "SAND": {
                "BT": 6041.300000000002,
                "CT": 207.1,
                "GP": 0.2,
                "IF": 287.00000000000006,
                "PL": 79.0,
                "TM": 92.4
            },
            "SYNCRD": {
                "PL": 230464.5
            },
            "WATER": {
                "BT": 25544046.700000025,
                "CT": 109569.29999999999,
                "GP": 283.6,
                "GS": 1119.6,
                "IF": 277170.7,
                "PL": 4956.6,
                "TM": 13963.400000000003,
                "WT": 1114609.0
            }
        },
        "FLARE": {
            "ACGAS": {
                "GP": 649.0999999999999
            },
            "ENTGAS": {
                "CT": 6.1
            },
            "GAS": {
                "BT": 37147.69999999996,
                "CT": 65.2,
                "GP": 1201.0999999999997,
                "GS": 437.2,
                "PL": 25.3,
                "TM": 152.3
            }
        },
        "FRAC": {
            "C3-MX": {
                "GP": -685.6
            },
            "C3-SP": {
                "GP": 685.6
            },
            "C4-SP": {
                "GP": 2041.8
            },
            "C5-SP": {
                "GP": 1247.6
            },
            "IC4-MX": {
                "GP": -2041.8
            },
            "IC5-MX": {
                "GP": -1247.6
            },
            "NC4-MX": {
                "GP": 0.0
            },
            "NC5-MX": {
                "GP": 0.0
            }
        },
        "FUEL": {
            "GAS": {
                "BT": 41219.400000000045,
                "CT": 717.4000000000001,
                "GP": 4837.6,
                "GS": 6376.4000000000015,
                "IF": 65086.100000000006,
                "PL": 56580.0,
                "TM": 13.7,
                "WT": 2.2
            }
        },
        "IMBAL": {
            "C2-MX": {
                "GP": 0.0,
                "GS": 0.0,
                "PL": 0.0
            },
            "C2-SP": {
                "GP": 0.0,
                "PL": 0.0
            },
            "C3-MX": {
                "GP": 0.0,
                "GS": 0.0,
                "PL": 0.0
            },
            "C3-SP": {
                "GP": 0.0,
                "TM": 0.0
            },
            "C4-MX": {
                "GP": 0.0,
                "GS": 0.0,
                "PL": 0.0
            },
            "C4-SP": {
                "GP": 0.0
            },
            "C5-MX": {
                "GP": 0.0,
                "GS": 0.0,
                "PL": 0.0
            },
            "C5-SP": {
                "GP": 0.0,
                "GS": 0.0
            },
            "CO2": {
                "BT": 0.0,
                "GP": 0.0
            },
            "CO2-SP": {
                "PL": 0.0
            },
            "HELIUM": {
                "BT": 0.0,
                "GP": 0.0
            },
            "OIL": {
                "BT": 0.0,
                "CT": 0.0,
                "IF": 0.0,
                "PL": 0.0,
                "TM": 0.0
            }
        },
        "INJ": {
            "AIR": {
                "IF": 701.0
            },
            "BRINE": {
                "IF": 3905317.7
            },
            "GAS": {
                "IF": 463.4
            },
            "POLYMER": {
                "IF": 828924.8999999998
            },
            "STEAM": {
                "IF": 905362.8999999999
            },
            "WASTE": {
                "IF": 33416.2
            },
            "WATER": {
                "IF": 28320712.299999963
            }
        },
        "INVADJ": {
            "C4-SP": {
                "PL": -1.9
            },
            "COND": {
                "PL": -199.5
            },
            "OIL": {
                "PL": 504.29999999999995
            },
            "WATER": {
                "PL": -173.60000000000002
            }
        },
        "INVCL": {
            "C2-MX": {
                "GP": 45.6
            },
            "C2-SP": {
                "PL": 1118.8
            },
            "C3-MX": {
                "GP": 2076.9
            },
            "C3-SP": {
                "GP": 823.3
            },
            "C4-MX": {
                "GP": 150.3
            },
            "C4-SP": {
                "GP": 294.0,
                "PL": 442.2,
                "TM": 10970.600000000002
            },
            "C5-MX": {
                "GP": 79.4
            },
            "C5-SP": {
                "GP": 632.8
            },
            "CO2-SP": {
                "IF": 0.0
            },
            "COND": {
                "GP": 118.6,
                "GS": 1229.1,
                "IF": 6.0,
                "PL": 20091.500000000004,
                "TM": 159.4
            },
            "FSHWTR": {
                "IF": 830.7,
                "WT": 3588.0
            },
            "GAS": {
                "PL": 151808.6
            },
            "HELIUM": {
                "BT": 5.6,
                "GP": 10.6
            },
            "IC4-MX": {
                "GP": 244.6
            },
            "IC5-MX": {
                "GP": 0.0
            },
            "NC4-MX": {
                "GP": 641.6
            },
            "NC5-MX": {
                "GP": 403.0
            },
            "OIL": {
                "BT": 185457.70000000013,
                "CT": 8629.8,
                "IF": 455.9,
                "PL": 318400.9,
                "TM": 62259.69999999999
            },
            "WATER": {
                "BT": 252119.2000000003,
                "CT": 5947.3,
                "GP": 109.69999999999999,
                "GS": 172.9,
                "IF": 144253.79999999996,
                "PL": 173.3,
                "TM": 1726.7999999999997,
                "WT": 970.6999999999999
            }
        },
        "INVOP": {
            "C2-MX": {
                "GP": 42.800000000000004
            },
            "C2-SP": {
                "PL": 1118.8
            },
            "C3-MX": {
                "GP": 1869.8
            },
            "C3-SP": {
                "GP": 978.9
            },
            "C4-MX": {
                "GP": 106.3
            },
            "C4-SP": {
                "GP": 429.0,
                "PL": 581.2,
                "TM": 11060.5
            },
            "C5-MX": {
                "GP": 39.7
            },
            "C5-SP": {
                "GP": 558.8
            },
            "CO2-SP": {
                "IF": 0.0
            },
            "COND": {
                "GP": 166.00000000000003,
                "GS": 825.5999999999999,
                "IF": 6.0,
                "PL": 18701.3,
                "TM": 270.9
            },
            "FSHWTR": {
                "IF": 896.3,
                "WT": 3499.7
            },
            "GAS": {
                "PL": 151579.3
            },
            "HELIUM": {
                "BT": 4.699999999999999,
                "GP": 8.0
            },
            "IC4-MX": {
                "GP": 232.7
            },
            "IC5-MX": {
                "GP": 0.0
            },
            "NC4-MX": {
                "GP": 610.5
            },
            "NC5-MX": {
                "GP": 383.3
            },
            "OIL": {
                "BT": 187359.79999999996,
                "CT": 8254.6,
                "IF": 399.6,
                "PL": 326414.4,
                "TM": 59958.99999999999
            },
            "WATER": {
                "BT": 251328.80000000028,
                "CT": 5655.1,
                "GP": 96.0,
                "GS": 219.1,
                "IF": 141379.59999999998,
                "PL": 58.3,
                "TM": 1974.6999999999998,
                "WT": 1088.7
            }
        },
        "LDINJ": {
            "OIL": {
                "BT": 1802.8000000000002
            },
            "WATER": {
                "BT": 87179.99999999997,
                "IF": 0.0
            }
        },
        "LDINVADJ": {
            "OIL": {
                "BT": 10.0
            },
            "WATER": {
                "BT": -3854.2000000000025
            }
        },
        "LDINVCL": {
            "COND": {
                "BT": 2.6
            },
            "OIL": {
                "BT": 3360.300000000001
            },
            "WATER": {
                "BT": 616725.0000000003,
                "IF": 454.0
            }
        },
        "LDINVOP": {
            "COND": {
                "BT": 2.6
            },
            "OIL": {
                "BT": 3205.3000000000025
            },
            "WATER": {
                "BT": 581219.6000000006,
                "IF": 454.0
            }
        },
        "LDREC": {
            "OIL": {
                "BT": 1657.8000000000004
            },
            "WATER": {
                "BT": 47820.40000000007
            }
        },
        "PROC": {
            "C2-MX": {
                "GP": 131.9,
                "GS": 3.5
            },
            "C2-SP": {
                "GP": 1211.9
            },
            "C3-MX": {
                "GP": 11239.3,
                "GS": 7.0
            },
            "C3-SP": {
                "GP": 8188.9
            },
            "C4-MX": {
                "GP": 3471.0,
                "GS": 19.2
            },
            "C4-SP": {
                "GP": 6001.2
            },
            "C5-MX": {
                "GP": 1812.8,
                "GS": 66.0
            },
            "C5-SP": {
                "GP": 8209.300000000001,
                "GS": 0.0
            }
        },
        "PROD": {
            "CO2": {
                "BT": 418.8999999999999
            },
            "FSHWTR": {
                "WT": 1969712.4999999995
            },
            "GAS": {
                "BT": 296743.19999999745
            },
            "HELIUM": {
                "BT": 210.7
            },
            "N2": {
                "BT": 27445.700000000004
            },
            "OIL": {
                "BT": 1547924.9000000071
            },
            "WATER": {
                "BT": 24439532.09999992,
                "IF": 22.4,
                "WT": 1102562.5999999999
            }
        },
        "PURDISP": {
            "OIL": {
                "BT": 1993.1999999999998,
                "CT": 12.2,
                "GP": 0.0,
                "IF": 587.8,
                "TM": 19.6
            }
        },
        "PURREC": {
            "OIL": {
                "BT": 738.0,
                "CT": 879.1
            }
        },
        "REC": {
            "BRINE": {
                "IF": 3230308.4
            },
            "C2-MX": {
                "GP": 0.0,
                "PL": 101.1
            },
            "C2-SP": {
                "PL": 1211.9
            },
            "C3-MX": {
                "GP": 5970.5,
                "PL": 9279.4
            },
            "C3-SP": {
                "TM": 9281.7
            },
            "C4-MX": {
                "GP": 0.0
            },
            "C4-SP": {
                "BT": 574.9,
                "PL": 26019.199999999997,
                "TM": 23320.899999999998
            },
            "C5-MX": {
                "GP": 0.0,
                "PL": 918.8
            },
            "CO2": {
                "BT": 0.1,
                "GP": 394.8
            },
            "CO2-MX": {
                "IF": 726972.2999999999
            },
            "CO2-SP": {
                "IF": 35531.1,
                "PL": 35531.1
            },
            "COND": {
                "BT": 4740.5,
                "GS": 3479.6000000000004,
                "PL": 210323.19999999998,
                "TM": 18024.5
            },
            "FSHWTR": {
                "BT": 101247.4,
                "IF": 1785534.0000000002,
                "WT": 989540.0
            },
            "GAS": {
                "BT": 98150.60000000003,
                "CT": 782.6000000000001,
                "GP": 81534.29999999999,
                "GS": 233676.8,
                "IF": 67124.7,
                "PL": 4658592.0,
                "TM": 196.3,
                "WT": 2.2
            },
            "HELIUM": {
                "BT": 7.0,
                "GP": 181.8
            },
            "IC4-MX": {
                "GP": 2142.9,
                "PL": 656.7
            },
            "IC5-MX": {
                "GP": 1247.6
            },
            "N2": {
                "BT": 1559.8000000000002,
                "GP": 25991.9
            },
            "NC4-MX": {
                "GP": 282.3,
                "PL": 1736.3
            },
            "NC5-MX": {
                "GP": 0.0
            },
            "OIL": {
                "BT": 293396.4999999995,
                "CT": 165882.09999999998,
                "IF": 100.5,
                "PL": 3224482.5999999996,
                "TM": 1021654.4
            },
            "POLYMER": {
                "IF": 87341.2
            },
            "SAND": {
                "BT": 3.4
            },
            "SYNCRD": {
                "PL": 230355.9
            },
            "WASTE": {
                "IF": 33416.2
            },
            "WATER": {
                "BT": 1105534.2999999996,
                "CT": 109861.5,
                "GP": 297.3,
                "GS": 1073.4,
                "IF": 29251871.09999998,
                "PL": 5244.499999999999,
                "TM": 13715.500000000002,
                "WT": 6258.1
            }
        },
        "SHR": {
            "ACGAS": {
                "GP": 54.5
            },
            "C2-MX": {
                "GP": 37.1,
                "GS": 1.0
            },
            "C2-SP": {
                "GP": 341.0
            },
            "C3-MX": {
                "GP": 3058.5,
                "GS": 1.9
            },
            "C3-SP": {
                "GP": 2228.3999999999996
            },
            "C4-MX": {
                "GP": 824.9,
                "GS": 4.6
            },
            "C4-SP": {
                "GP": 1426.4
            },
            "C5-MX": {
                "GP": 374.7,
                "GS": 13.6
            },
            "C5-SP": {
                "GP": 1696.5,
                "GS": 0.0
            },
            "COND": {
                "BT": 67.9,
                "TM": 3.4
            },
            "OIL": {
                "BT": 0.0,
                "PL": 3616.7999999999997,
                "TM": 230.5
            }
        },
        "SHUTIN": {},
        "SPILL": {
            "OIL": {
                "BT": 0.3,
                "CT": 3.0
            },
            "WATER": {
                "BT": 0.5
            }
        },
        "STINJ": {
            "CO2-MX": {
                "IF": 749511.7999999998
            },
            "GAS": {
                "IF": 1477.0
            }
        },
        "STINVCL": {
            "C3-MX": {
                "IF": 0.0
            },
            "CO2-MX": {
                "IF": 42532627.7
            },
            "GAS": {
                "IF": 7229.9
            }
        },
        "STINVOP": {
            "C3-MX": {
                "IF": 0.0
            },
            "CO2-MX": {
                "IF": 42301460.8
            },
            "GAS": {
                "IF": 6388.299999999999
            }
        },
        "STREC": {
            "C3-MX": {
                "BT": 0.4
            },
            "CO2-MX": {
                "BT": 70008.30000000002
            },
            "GAS": {
                "BT": 5572.799999999998
            }
        },
        "VENT": {
            "C3-MX": {
                "BT": 0.4
            },
            "CO2": {
                "BT": 24.099999999999998,
                "GP": 394.8
            },
            "CO2-MX": {
                "BT": 5427.199999999999
            },
            "ENTGAS": {
                "CT": 1.1
            },
            "GAS": {
                "BT": 14013.400000000232,
                "GP": 486.7,
                "GS": 76.29999999999998,
                "IF": 24.9,
                "PL": 1.2,
                "TM": 30.3
            },
            "N2": {
                "BT": 1453.8,
                "GP": 25991.9
            }
        }
    }
}